tpm_multicast_client/__init__.py
tpm_multicast_client/__main__.py
tpm_multicast_client/client.py
tpm_multicast_client/server.py
tpm_multicast_client/unpack.py
sdss_tpm_multicast_client-0.3.1.dist-info/METADATA
sdss_tpm_multicast_client-0.3.1.dist-info/WHEEL
sdss_tpm_multicast_client-0.3.1.dist-info/entry_points.txt
sdss_tpm_multicast_client-0.3.1.dist-info/RECORD
