Metadata-Version: 2.1
Name: sdss-tpm-multicast-client
Version: 0.3.1
Summary: TPM multicast client
License: BSD 3-Clause
Author: José Sánchez-Gallego
Author-email: gallegoj@uw.edu
Requires-Python: >=3.10,<4.0
Classifier: License :: Other/Proprietary License
Classifier: Programming Language :: Python :: 3
Classifier: Programming Language :: Python :: 3.10
Classifier: Programming Language :: Python :: 3.11
Classifier: Programming Language :: Python :: 3.12
Requires-Dist: sdsstools (>=1.0.0,<2.0.0)
